{"units":{"WEEK":{"one":"{0} εβδομάδα","other":"{0} εβδομάδες"},"YEAR":{"one":"{0} έτος","other":"{0} έτη"},"MONTH":{"one":"{0} μήνας","other":"{0} μήνες"},"SECOND":{"one":"{0} δευτερόλεπτο","other":"{0} δευτερόλεπτα"},"MINUTE":{"one":"{0} λεπτό","other":"{0} λεπτά"},"HOUR":{"one":"{0} ώρα","other":"{0} ώρες"},"DAY":{"one":"{0} ημέρα","other":"{0} ημέρες"}},"pastUnits":{"WEEK":{"one":"Πριν από {0} εβδομάδα","other":"Πριν από {0} εβδομάδες"},"YEAR":{"one":"Πριν από {0} έτος","other":"Πριν από {0} έτη"},"MONTH":{"one":"Πριν από {0} μήνα","other":"Πριν από {0} μήνες"},"SECOND":{"one":"Πριν από {0} δευτερόλεπτο","other":"Πριν από {0} δευτερόλεπτα"},"MINUTE":{"one":"Πριν από {0} λεπτό","other":"Πριν από {0} λεπτά"},"HOUR":{"one":"Πριν από {0} ώρα","other":"Πριν από {0} ώρες"},"DAY":{"one":"Πριν από {0} ημέρα","other":"Πριν από {0} ημέρες"}},"futureUnits":{"WEEK":{"one":"Σε {0} εβδομάδα","other":"Σε {0} εβδομάδες"},"YEAR":{"one":"Σε {0} έτος","other":"Σε {0} έτη"},"MONTH":{"one":"Σε {0} μήνα","other":"Σε {0} μήνες"},"SECOND":{"one":"Σε {0} δευτερόλεπτο","other":"Σε {0} δευτερόλεπτα"},"MINUTE":{"one":"Σε {0} λεπτό","other":"Σε {0} λεπτά"},"HOUR":{"one":"Σε {0} ώρα","other":"Σε {0} ώρες"},"DAY":{"one":"Σε {0} ημέρα","other":"Σε {0} ημέρες"}},"shortUnits":{"WEEK":{"one":"{0} εβδομάδα","other":"{0} εβδομάδες"},"YEAR":{"one":"{0} έτος","other":"{0} έτη"},"MONTH":{"one":"{0} μήνας","other":"{0} μήνες"},"SECOND":{"one":"{0} δευτερόλεπτο","other":"{0} δευτερόλεπτα"},"MINUTE":{"one":"{0} λεπτό","other":"{0} λεπτά"},"HOUR":{"one":"{0} ώρα","other":"{0} ώρες"},"DAY":{"one":"{0} ημέρα","other":"{0} ημέρες"}}}