{"name":"ml","units":{"hour":{"one":"{0} മണിക്കൂര്‍","other":"{0} മണിക്കൂര്‍"},"minute":{"one":"{0} മിനിട്ട്","other":"{0} മിനിട്ട്"},"week":{"one":"{0} ആഴ്ച","other":"{0} ആഴ്ച"},"month":{"one":"{0} മാസം","other":"{0} മാസം"},"second":{"one":"{0} സെക്കന്റ്","other":"{0} സെക്കന്റ്"},"day":{"one":"{0} ദിവസം","other":"{0} ദിവസം"},"year":{"one":"{0} വര്‍ഷം","other":"{0} വര്‍ഷം"}},"pastUnits":{"hour":{"1":"1 മണിക്കൂര്‍ മുമ്പ്","0":"0 മണിക്കൂര്‍ മുമ്പ്","other":"{0} മണിക്കൂര്‍ മുമ്പ്"},"minute":{"1":"1 മിനിറ്റ് മുമ്പ്","0":"0 മിനിറ്റ് മുമ്പ്","other":"{0} മിനിറ്റ് മുമ്പ്"},"week":{"1":"1 ആഴ്ച മുമ്പ്","0":"0 ആഴ്ച മുമ്പ്","other":"{0} ആഴ്ച മുമ്പ്"},"month":{"1":"1 മാസം മുമ്പ്","0":"0 മാസം മുമ്പ്","other":"{0} മാസം മുമ്പ്"},"second":{"1":"1 സെക്കന്‍റ് മുമ്പ്","0":"0 സെക്കന്‍റ് മുമ്പ്","other":"{0} സെക്കന്‍റ് മുമ്പ്"},"day":{"1":"1 ദിവസം മുമ്പ്","0":"0 ദിവസം മുമ്പ്","other":"{0} ദിവസം മുമ്പ്"},"year":{"1":"1 വര്‍ഷം മുമ്പ്","0":"0 വര്‍ഷം മുമ്പ്","other":"{0} വര്‍ഷം മുമ്പ്"}},"futureUnits":{"hour":{"1":"1 മണിക്കൂറില്‍","0":"0 മണിക്കൂറില്‍","other":"{0} മണിക്കൂറില്‍"},"minute":{"1":"1 മിനിറ്റിനുള്ളില്‍","0":"0 മിനിറ്റില്‍","other":"{0} മിനിറ്റിനുള്ളില്‍"},"week":{"1":"1 ആഴ്ചയില്‍","0":"0 ആഴ്ചയില്‍","other":"{0} ആഴ്ചയില്‍"},"month":{"1":"1 മാസത്തില്‍","0":"0 മാസത്തില്‍","other":"{0} മാസത്തില്‍"},"second":{"1":"1 സെക്കന്‍ഡില്‍","0":"0 സെക്കന്‍ഡില്‍","other":"{0} സെക്കന്‍ഡില്‍"},"day":{"1":"1 ദിവസത്തില്‍","0":"0 ദിവസത്തില്‍","other":"{0} ദിവസത്തില്‍"},"year":{"1":"1 വര്‍ഷത്തില്‍","0":"0 വര്‍ഷത്തില്‍","other":"{0} വര്‍ഷത്തില്‍"}},"shortUnits":{"hour":{"1":"1 മണിക്കൂര്‍‌","0":"0 മണിക്കൂര്‍","other":"{0} മണിക്കൂര്‍"},"minute":{"1":"1 മിനിറ്റ്","0":"0 മിനിറ്റ്","other":"{0} മിനിറ്റ്"},"week":{"1":"1 ആഴ്‌ച","0":"0 ആഴ്‌ച","other":"{0} ആഴ്‌ച"},"month":{"1":"1 മാസം","0":"0 മാസങ്ങള്‍","other":"{0} മാസം"},"second":{"1":"1 സെക്കന്‍റ്","0":"0 സെക്കന്‍റ്","other":"{0} സെക്കന്‍റ്"},"day":{"1":"1 ദിവസം","0":"0 ദിവസം‌","other":"{0} ദിവസം‌"},"year":{"1":"1 വര്‍ഷം","0":"0 വര്‍‌ഷം","other":"{0} വര്‍‌ഷം"}}}