{"name":"no","units":{"hour":{"one":"{0} time","other":"{0} timer"},"minute":{"one":"{0} minutt","other":"{0} minutter"},"week":{"one":"{0} uke","other":"{0} uker"},"month":{"one":"{0} måned","other":"{0} måneder"},"second":{"one":"{0} sekund","other":"{0} sekunder"},"day":{"one":"{0} dag","other":"{0} dager"},"year":{"one":"{0} år","other":"{0} år"}},"pastUnits":{},"futureUnits":{},"shortUnits":{"hour":{"one":"{0} t","other":"{0} t"},"minute":{"one":"{0} min","other":"{0} min"},"week":{"one":"{0} uke","other":"{0} uker"},"month":{"one":"{0} md.","other":"{0} md."},"second":{"one":"{0} sek","other":"{0} sek"},"day":{"one":"{0} dag","other":"{0} dager"},"year":{"one":"{0} år","other":"{0} år"}}}