{"units":{"hour":{"1":"1 గంట","one":"{0} గంట","0":"0 గంటలు","other":"{0} గంటలు"},"second":{"1":"1 సెకన్","one":"{0} క్షణం","0":"0 సెకన్లు","other":"{0} సెకన్లు"},"month":{"1":"1 నెల","one":"{0} నెల","0":"0 నెలలు","other":"{0} నెలలు"},"week":{"1":"1 వారం","one":"{0} వారం","0":"0 వారాలు","other":"{0} weeks"},"minute":{"1":"1 నిమిషం","one":"{0} నిమిషం","0":"0 నిమిషాలు","other":"{0} నిమిషాలు"},"day":{"1":"1 రోజు","one":"{0} రోజు","0":"0 రోజులు","other":"{0} days"},"year":{"1":"1 సంవత్సరం","one":"{0} సంవత్సరం","0":"0 సంవత్సరాలు","other":"{0} సంవత్సరాలు"}},"pastUnits":{"hour":{"1":"1 గంట క్రితం","0":"0 గంటల క్రితం","other":"{0} గంటల క్రితం"},"second":{"1":"1 సెకను క్రితం","0":"0 సెకన్ల క్రితం","other":"{0} సెకన్ల క్రితం"},"month":{"1":"1 నెల క్రితం","0":"0 నెలల క్రితం","other":"{0} నెలల క్రితం"},"week":{"1":"1 వారం క్రితం","0":"0 వారాల క్రితం","other":"{0} వారాల క్రితం"},"minute":{"1":"1 నిమిషం క్రితం","0":"0 నిమిషాల క్రితం","other":"{0} నిమిషాల క్రితం"},"day":{"1":"1 రోజు క్రితం","0":"0 రోజుల క్రితం","other":"{0} రోజుల క్రితం"},"year":{"1":"1 సంవత్సరం క్రితం","0":"0 సంవత్సరాల క్రితం","other":"{0} సంవత్సరాల క్రితం"}},"futureUnits":{"hour":{"1":"1 గంటలో","0":"0 గంటల్లో","other":"{0} గంటల్లో"},"second":{"1":"1 సెకన్‌లో","0":"0 సెకన్లలో","other":"{0} సెకన్లలో"},"month":{"1":"1 నెలలో","0":"0 నెలల్లో","other":"{0} నెలల్లో"},"week":{"1":"1 వారంలో","0":"0 వారాల్లో","other":"{0} వారాల్లో"},"minute":{"1":"1 నిమిషంలో","0":"0 నిమిషాల్లో","other":"{0} నిమిషాల్లో"},"day":{"1":"1 రోజులో","0":"0 రోజుల్లో","other":"{0} రోజుల్లో"},"year":{"1":"1 సంవత్సరంలో","0":"0 సంవత్సరాల్లో","other":"{0} సంవత్సరాల్లో"}},"shortUnits":{"hour":{"1":"1 గంట","0":"0 గంటలు","other":"{0} గంటలు"},"second":{"1":"1 సెకను","0":"0 సెకన్లు","other":"{0} సెకన్లు"},"month":{"1":"1 నెల","0":"0 నెలలు","other":"{0} నెలలు"},"week":{"1":"1 వా","0":"0 వారాలు","other":"{0} వారాలు"},"minute":{"1":"1 నిమిషం","0":"0 నిమిషాలు","other":"{0} నిమిషాలు"},"day":{"1":"1 రోజు","0":"0 రోజులు","other":"{0} days"},"year":{"1":"1 సంవత్సరం","0":"0 సంవత్సరాలు","other":"{0} సంవత్సరాలు"}}}